scripts/.gitkeep
scripts/__init__.py
scripts/_version.py
scripts/baseline_modeling.py
scripts/explainability.py
scripts/modeling_config.py
scripts/train_single.py
scripts/train_stacking.py
scripts/tune_hyperparameters.py
scripts/utils_dqc.py
scripts/utils_dvc.py
scripts/utils_eda.py
scripts/utils_etl.py
scripts/utils_validation.py
scripts/models/__init__.py
scripts/models/base.py
scripts/models/lightgbm_model.py
scripts/models/registry.py
scripts/models/stacking_model.py
scripts/models/xgboost_model.py
scripts/training/__init__.py
scripts/training/pipeline.py
scripts/training/trainer.py
predict_sales_ml-1.0.0.dist-info/METADATA
predict_sales_ml-1.0.0.dist-info/WHEEL
predict_sales_ml-1.0.0.dist-info/top_level.txt
predict_sales_ml-1.0.0.dist-info/RECORD
