Metadata-Version: 2.4
Name: predict-sales-ml
Version: 1.0.0
Summary: ML toolkit for time-series sales prediction with feature engineering, validation, and hyperparameter optimization
Author: Eugene Malyukevich
Keywords: machine-learning,time-series,sales-prediction,feature-engineering,hyperparameter-optimization
Requires-Python: <3.12,>=3.11
Requires-Dist: lightgbm>=4.0.0
Requires-Dist: matplotlib>=3.10.7
Requires-Dist: mlflow>=2.0.0
Requires-Dist: numpy>=2.3.5
Requires-Dist: optuna>=4.6.0
Requires-Dist: pandas>=2.3.3
Requires-Dist: pyarrow<21.0.0,>=15.0.0
Requires-Dist: pyyaml>=6.0.0
Requires-Dist: python-dotenv>=1.0.0
Requires-Dist: scikit-learn>=1.7.2
Requires-Dist: shap>=0.50.0
Requires-Dist: scipy>=1.11.0
Requires-Dist: tqdm>=4.66.0
Requires-Dist: xgboost>=3.1.2
